[
  {
    "player_id": "00-0026158",
    "player_name": "J.Flacco",
    "player_display_name": "Joe Flacco",
    "headshot_url": "https://static.www.nfl.com/image/private/f_auto,q_auto/league/zg6azyjniovtgb7vdssz",
    "total_ppr": 100.84,
    "ppr_ppg": 20.168,
    "consistency_rtg": 0.1837
  },
  {
    "player_id": "00-0035228",
    "player_name": "K.Murray",
    "player_display_name": "Kyler Murray",
    "headshot_url": "https://static.www.nfl.com/image/private/f_auto,q_auto/league/ad68dbv2eqakttaqwppv",
    "total_ppr": 146.36,
    "ppr_ppg": 18.295,
    "consistency_rtg": 0.2239
  },
  {
    "player_id": "00-0029263",
    "player_name": "R.Wilson",
    "player_display_name": "Russell Wilson",
    "headshot_url": "https://static.www.nfl.com/image/private/f_auto,q_auto/league/gebzv2aljujgleboe4ns",
    "total_ppr": 256.9,
    "ppr_ppg": 17.1267,
    "consistency_rtg": 0.2651
  },
  {
    "player_id": "00-0026498",
    "player_name": "M.Stafford",
    "player_display_name": "Matthew Stafford",
    "headshot_url": "https://static.www.nfl.com/image/private/f_auto,q_auto/league/icjfdfsncqlsqe49iujv",
    "total_ppr": 243.1,
    "ppr_ppg": 16.2067,
    "consistency_rtg": 0.2863
  },
  {
    "player_id": "00-0034857",
    "player_name": "J.Allen",
    "player_display_name": "Josh Allen",
    "headshot_url": "https://static.www.nfl.com/image/private/f_auto,q_auto/league/ghmmndgjefpxziks7ntf",
    "total_ppr": 394.64,
    "ppr_ppg": 23.2141,
    "consistency_rtg": 0.3209
  },
  {
    "player_id": "00-0036264",
    "player_name": "J.Love",
    "player_display_name": "Jordan Love",
    "headshot_url": "https://static.www.nfl.com/image/private/f_auto,q_auto/league/sbnqsffanu76dcz1tugs",
    "total_ppr": 319.06,
    "ppr_ppg": 18.7682,
    "consistency_rtg": 0.329
  },
  {
    "player_id": "00-0036963",
    "player_name": "A.St. Brown",
    "player_display_name": "Amon-Ra St. Brown",
    "headshot_url": "https://static.www.nfl.com/image/private/f_auto,q_auto/league/ubbam2rpn7xfbhvzvjyn",
    "total_ppr": 330.9,
    "ppr_ppg": 20.6813,
    "consistency_rtg": 0.3317
  },
  {
    "player_id": "00-0033873",
    "player_name": "P.Mahomes",
    "player_display_name": "Patrick Mahomes",
    "headshot_url": "https://static.www.nfl.com/image/private/f_auto,q_auto/league/oagzjdsdoezmp6frggrn",
    "total_ppr": 280.22,
    "ppr_ppg": 17.5138,
    "consistency_rtg": 0.3608
  },
  {
    "player_id": "00-0036389",
    "player_name": "J.Hurts",
    "player_display_name": "Jalen Hurts",
    "headshot_url": "https://static.www.nfl.com/image/private/f_auto,q_auto/league/aityegmlyh53aifbssbp",
    "total_ppr": 356.82,
    "ppr_ppg": 20.9894,
    "consistency_rtg": 0.3729
  },
  {
    "player_id": "00-0029604",
    "player_name": "K.Cousins",
    "player_display_name": "Kirk Cousins",
    "headshot_url": "https://static.www.nfl.com/image/private/f_auto,q_auto/league/viuxnyezrwdfjnxsfssb",
    "total_ppr": 149.74,
    "ppr_ppg": 18.7175,
    "consistency_rtg": 0.3733
  },
  {
    "player_id": "00-0036252",
    "player_name": "M.Pittman",
    "player_display_name": "Michael Pittman",
    "headshot_url": "https://static.www.nfl.com/image/private/f_auto,q_auto/league/wnymcombo2plamteihiy",
    "total_ppr": 252.2,
    "ppr_ppg": 15.7625,
    "consistency_rtg": 0.374
  },
  {
    "player_id": "00-0034855",
    "player_name": "B.Mayfield",
    "player_display_name": "Baker Mayfield",
    "headshot_url": "https://static.www.nfl.com/image/private/f_auto,q_auto/league/haglbmidyaxtimhctzlp",
    "total_ppr": 274.06,
    "ppr_ppg": 16.1212,
    "consistency_rtg": 0.3768
  },
  {
    "player_id": "00-0036212",
    "player_name": "T.Tagovailoa",
    "player_display_name": "Tua Tagovailoa",
    "headshot_url": "https://static.www.nfl.com/image/private/f_auto,q_auto/league/dyrrl1knhcxqjwuvhcwm",
    "total_ppr": 272.36,
    "ppr_ppg": 16.0212,
    "consistency_rtg": 0.3824
  },
  {
    "player_id": "00-0037256",
    "player_name": "R.White",
    "player_display_name": "Rachaad White",
    "headshot_url": "https://static.www.nfl.com/image/private/f_auto,q_auto/league/uiqqvw00vpykdylgu7d4",
    "total_ppr": 267.9,
    "ppr_ppg": 15.7588,
    "consistency_rtg": 0.3929
  },
  {
    "player_id": "00-0033897",
    "player_name": "J.Mixon",
    "player_display_name": "Joe Mixon",
    "headshot_url": "https://static.www.nfl.com/image/private/f_auto,q_auto/league/pbijtl1blfdkvmwl4rsp",
    "total_ppr": 267,
    "ppr_ppg": 15.7059,
    "consistency_rtg": 0.3964
  },
  {
    "player_id": "00-0033280",
    "player_name": "C.McCaffrey",
    "player_display_name": "Christian McCaffrey",
    "headshot_url": "https://static.www.nfl.com/image/private/f_auto,q_auto/league/navqer4chxxut5povzzw",
    "total_ppr": 391.3,
    "ppr_ppg": 24.4563,
    "consistency_rtg": 0.397
  },
  {
    "player_id": "00-0033106",
    "player_name": "J.Goff",
    "player_display_name": "Jared Goff",
    "headshot_url": "https://static.www.nfl.com/image/private/f_auto,q_auto/league/nyitt4ybuzopzjzddafi",
    "total_ppr": 289.1,
    "ppr_ppg": 17.0059,
    "consistency_rtg": 0.3994
  },
  {
    "player_id": "00-0037239",
    "player_name": "C.Olave",
    "player_display_name": "Chris Olave",
    "headshot_url": "https://static.www.nfl.com/image/private/f_auto,q_auto/league/vtfhbyz1ofg6cgxxulw4",
    "total_ppr": 231.3,
    "ppr_ppg": 14.4563,
    "consistency_rtg": 0.3998
  },
  {
    "player_id": "00-0037834",
    "player_name": "B.Purdy",
    "player_display_name": "Brock Purdy",
    "headshot_url": "https://static.www.nfl.com/image/private/f_auto,q_auto/league/hdwbdlyiose4znenx5ed",
    "total_ppr": 295.6,
    "ppr_ppg": 18.475,
    "consistency_rtg": 0.4041
  },
  {
    "player_id": "00-0033906",
    "player_name": "A.Kamara",
    "player_display_name": "Alvin Kamara",
    "headshot_url": "https://static.www.nfl.com/image/private/f_auto,q_auto/league/tl9enad6kiwv6cukf4vt",
    "total_ppr": 233,
    "ppr_ppg": 17.9231,
    "consistency_rtg": 0.4047
  },
  {
    "player_id": "00-0033040",
    "player_name": "T.Hill",
    "player_display_name": "Tyreek Hill",
    "headshot_url": "https://static.www.nfl.com/image/private/f_auto,q_auto/league/lsszbdnkusxc7mduw5be",
    "total_ppr": 376.4,
    "ppr_ppg": 23.525,
    "consistency_rtg": 0.4112
  },
  {
    "player_id": "00-0036971",
    "player_name": "T.Lawrence",
    "player_display_name": "Trevor Lawrence",
    "headshot_url": "https://static.www.nfl.com/image/private/f_auto,q_auto/league/angjglqlgj2txh25se5j",
    "total_ppr": 262.54,
    "ppr_ppg": 16.4088,
    "consistency_rtg": 0.4211
  },
  {
    "player_id": "00-0037840",
    "player_name": "K.Williams",
    "player_display_name": "Kyren Williams",
    "headshot_url": "https://static.www.nfl.com/image/private/f_auto,q_auto/league/emynpilqbr8huoh6vmhg",
    "total_ppr": 255,
    "ppr_ppg": 21.25,
    "consistency_rtg": 0.4267
  },
  {
    "player_id": "00-0033921",
    "player_name": "C.Godwin",
    "player_display_name": "Chris Godwin",
    "headshot_url": "https://static.www.nfl.com/image/private/f_auto,q_auto/league/rfdampf12giyojipbcxl",
    "total_ppr": 209.2,
    "ppr_ppg": 12.3059,
    "consistency_rtg": 0.4278
  },
  {
    "player_id": "00-0036407",
    "player_name": "J.Jeudy",
    "player_display_name": "Jerry Jeudy",
    "headshot_url": "https://static.www.nfl.com/image/private/f_auto,q_auto/league/f0jdlnl6wy63qx4oeyzi",
    "total_ppr": 141.8,
    "ppr_ppg": 8.8625,
    "consistency_rtg": 0.43
  },
  {
    "player_id": "00-0036223",
    "player_name": "J.Taylor",
    "player_display_name": "Jonathan Taylor",
    "headshot_url": "https://static.www.nfl.com/image/private/f_auto,q_auto/league/xt7jhqpyb4may7k5kedb",
    "total_ppr": 156.4,
    "ppr_ppg": 15.64,
    "consistency_rtg": 0.4302
  },
  {
    "player_id": "00-0037228",
    "player_name": "J.Warren",
    "player_display_name": "Jaylen Warren",
    "headshot_url": "https://static.www.nfl.com/image/private/f_auto,q_auto/league/q6zstqy99al3sghrufey",
    "total_ppr": 196.4,
    "ppr_ppg": 11.5529,
    "consistency_rtg": 0.4309
  },
  {
    "player_id": "00-0037740",
    "player_name": "G.Wilson",
    "player_display_name": "Garrett Wilson",
    "headshot_url": "https://static.www.nfl.com/image/private/f_auto,q_auto/league/llgosx4tokddwnyrgvbx",
    "total_ppr": 213.2,
    "ppr_ppg": 12.5412,
    "consistency_rtg": 0.4352
  },
  {
    "player_id": "00-0039067",
    "player_name": "R.Rice",
    "player_display_name": "Rashee Rice",
    "headshot_url": "https://static.www.nfl.com/image/private/f_auto,q_auto/league/zjgi60dvmj5ogvanp201",
    "total_ppr": 212.5,
    "ppr_ppg": 13.2812,
    "consistency_rtg": 0.4391
  },
  {
    "player_id": "00-0034796",
    "player_name": "L.Jackson",
    "player_display_name": "Lamar Jackson",
    "headshot_url": "https://static.www.nfl.com/image/private/f_auto,q_auto/league/wj1fwvvkjaqztm56ybzu",
    "total_ppr": 331.22,
    "ppr_ppg": 20.7013,
    "consistency_rtg": 0.4417
  },
  {
    "player_id": "00-0036613",
    "player_name": "J.Waddle",
    "player_display_name": "Jaylen Waddle",
    "headshot_url": "https://static.www.nfl.com/image/private/f_auto,q_auto/league/qjsz2h6shbdnksctzeka",
    "total_ppr": 198.6,
    "ppr_ppg": 14.1857,
    "consistency_rtg": 0.453
  },
  {
    "player_id": "00-0036265",
    "player_name": "A.Dillon",
    "player_display_name": "A.J. Dillon",
    "headshot_url": "https://static.www.nfl.com/image/private/f_auto,q_auto/league/dydcqdx4leta4rudagkq",
    "total_ppr": 117.6,
    "ppr_ppg": 7.84,
    "consistency_rtg": 0.4591
  },
  {
    "player_id": "00-0036358",
    "player_name": "C.Lamb",
    "player_display_name": "CeeDee Lamb",
    "headshot_url": "https://static.www.nfl.com/image/private/f_auto,q_auto/league/cqygs9e4ynnjdxstdfjq",
    "total_ppr": 405.2,
    "ppr_ppg": 23.8353,
    "consistency_rtg": 0.4599
  },
  {
    "player_id": "00-0035685",
    "player_name": "D.Montgomery",
    "player_display_name": "David Montgomery",
    "headshot_url": "https://static.www.nfl.com/image/private/f_auto,q_auto/league/grd20lxzonco9jyg3ful",
    "total_ppr": 207.2,
    "ppr_ppg": 14.8,
    "consistency_rtg": 0.4629
  },
  {
    "player_id": "00-0035261",
    "player_name": "T.Pollard",
    "player_display_name": "Tony Pollard",
    "headshot_url": "https://static.www.nfl.com/image/private/f_auto,q_auto/league/pqhmih6cdyb3yqfd1dmb",
    "total_ppr": 222.6,
    "ppr_ppg": 13.0941,
    "consistency_rtg": 0.4659
  },
  {
    "player_id": "00-0031280",
    "player_name": "D.Carr",
    "player_display_name": "Derek Carr",
    "headshot_url": "https://static.www.nfl.com/image/private/f_auto,q_auto/league/cffbp9sqfioxa2jk2oqf",
    "total_ppr": 241.12,
    "ppr_ppg": 14.1835,
    "consistency_rtg": 0.4684
  },
  {
    "player_id": "00-0035229",
    "player_name": "T.Hockenson",
    "player_display_name": "T.J. Hockenson",
    "headshot_url": "https://static.www.nfl.com/image/private/f_auto,q_auto/league/exbnbnkgkhp9tlt10wig",
    "total_ppr": 219,
    "ppr_ppg": 14.6,
    "consistency_rtg": 0.4692
  },
  {
    "player_id": "00-0033077",
    "player_name": "D.Prescott",
    "player_display_name": "Dak Prescott",
    "headshot_url": "https://static.www.nfl.com/image/private/f_auto,q_auto/league/knx0jxponzfkusnyvjkn",
    "total_ppr": 342.84,
    "ppr_ppg": 20.1671,
    "consistency_rtg": 0.4695
  },
  {
    "player_id": "00-0030565",
    "player_name": "G.Smith",
    "player_display_name": "Geno Smith",
    "headshot_url": "https://static.www.nfl.com/image/private/f_auto,q_auto/league/bxp32udtvwnpu3rl2cht",
    "total_ppr": 227.26,
    "ppr_ppg": 15.1507,
    "consistency_rtg": 0.4703
  },
  {
    "player_id": "00-0038543",
    "player_name": "J.Smith-Njigba",
    "player_display_name": "Jaxon Smith-Njigba",
    "headshot_url": "https://static.www.nfl.com/image/private/f_auto,q_auto/league/r65p3l8nq7v4l9htqsud",
    "total_ppr": 149.8,
    "ppr_ppg": 8.8118,
    "consistency_rtg": 0.4745
  },
  {
    "player_id": "00-0034775",
    "player_name": "C.Kirk",
    "player_display_name": "Christian Kirk",
    "headshot_url": "https://static.www.nfl.com/image/private/f_auto,q_auto/league/ersmmtjmjlpsy9lmjvde",
    "total_ppr": 150.26,
    "ppr_ppg": 12.5217,
    "consistency_rtg": 0.4777
  },
  {
    "player_id": "00-0039163",
    "player_name": "C.Stroud",
    "player_display_name": "C.J. Stroud",
    "headshot_url": "https://static.www.nfl.com/image/private/f_auto,q_auto/league/u7g6u23cyjzpvayvwzhi",
    "total_ppr": 275.02,
    "ppr_ppg": 18.3347,
    "consistency_rtg": 0.4783
  },
  {
    "player_id": "00-0036555",
    "player_name": "C.Hubbard",
    "player_display_name": "Chuba Hubbard",
    "headshot_url": "https://static.www.nfl.com/image/private/f_auto,q_auto/league/f7xzicbrj7lacu7ytzd9",
    "total_ppr": 182.5,
    "ppr_ppg": 10.7353,
    "consistency_rtg": 0.4786
  },
  {
    "player_id": "00-0036261",
    "player_name": "B.Aiyuk",
    "player_display_name": "Brandon Aiyuk",
    "headshot_url": "https://static.www.nfl.com/image/private/f_auto,q_auto/league/mprcyhqhfgzi57ebelbz",
    "total_ppr": 249.2,
    "ppr_ppg": 15.575,
    "consistency_rtg": 0.4863
  },
  {
    "player_id": "00-0036328",
    "player_name": "A.Gibson",
    "player_display_name": "Antonio Gibson",
    "headshot_url": "https://static.www.nfl.com/image/private/f_auto,q_auto/league/c5aij3m4bakia6ygjqux",
    "total_ppr": 127.4,
    "ppr_ppg": 7.9625,
    "consistency_rtg": 0.4865
  },
  {
    "player_id": "00-0037197",
    "player_name": "I.Pacheco",
    "player_display_name": "Isiah Pacheco",
    "headshot_url": "https://static.www.nfl.com/image/private/f_auto,q_auto/league/rzr8nxjunjeiv8bjir59",
    "total_ppr": 213.9,
    "ppr_ppg": 15.2786,
    "consistency_rtg": 0.491
  },
  {
    "player_id": "00-0036355",
    "player_name": "J.Herbert",
    "player_display_name": "Justin Herbert",
    "headshot_url": "https://static.www.nfl.com/image/private/f_auto,q_auto/league/fwjdvww4dv36k8tvsws6",
    "total_ppr": 234.16,
    "ppr_ppg": 18.0123,
    "consistency_rtg": 0.4912
  },
  {
    "player_id": "00-0036997",
    "player_name": "J.Williams",
    "player_display_name": "Javonte Williams",
    "headshot_url": "https://static.www.nfl.com/image/private/f_auto,q_auto/league/zurpblacsps47csmsyep",
    "total_ppr": 179.2,
    "ppr_ppg": 11.2,
    "consistency_rtg": 0.4922
  },
  {
    "player_id": "00-0035659",
    "player_name": "T.McLaurin",
    "player_display_name": "Terry McLaurin",
    "headshot_url": "https://static.www.nfl.com/image/private/f_auto,q_auto/league/jpprw1itmmg5nhrdwony",
    "total_ppr": 203.2,
    "ppr_ppg": 11.9529,
    "consistency_rtg": 0.4936
  },
  {
    "player_id": "00-0039146",
    "player_name": "J.Reed",
    "player_display_name": "Jayden Reed",
    "headshot_url": "https://static.www.nfl.com/image/private/f_auto,q_auto/league/hotj0rhtzqtfckgt7xue",
    "total_ppr": 217.2,
    "ppr_ppg": 13.575,
    "consistency_rtg": 0.4954
  },
  {
    "player_id": "00-0034753",
    "player_name": "M.Andrews",
    "player_display_name": "Mark Andrews",
    "headshot_url": "https://static.www.nfl.com/image/private/f_auto,q_auto/league/cv7h66mkpoalli9wfdqp",
    "total_ppr": 135.4,
    "ppr_ppg": 13.54,
    "consistency_rtg": 0.4954
  },
  {
    "player_id": "00-0036912",
    "player_name": "D.Smith",
    "player_display_name": "DeVonta Smith",
    "headshot_url": "https://static.www.nfl.com/image/private/f_auto,q_auto/league/f8nowzare3wd2qw4jx7d",
    "total_ppr": 227.6,
    "ppr_ppg": 14.225,
    "consistency_rtg": 0.4955
  },
  {
    "player_id": "00-0036945",
    "player_name": "J.Fields",
    "player_display_name": "Justin Fields",
    "headshot_url": "https://static.www.nfl.com/image/private/f_auto,q_auto/league/y3irxvjwpyiavrtzay80",
    "total_ppr": 230.18,
    "ppr_ppg": 17.7062,
    "consistency_rtg": 0.4975
  },
  {
    "player_id": "00-0037267",
    "player_name": "J.Ford",
    "player_display_name": "Jerome Ford",
    "headshot_url": "https://static.www.nfl.com/image/private/f_auto,q_auto/league/djggmwo5v8osoboiseo2",
    "total_ppr": 213.2,
    "ppr_ppg": 12.5412,
    "consistency_rtg": 0.5012
  },
  {
    "player_id": "00-0034844",
    "player_name": "S.Barkley",
    "player_display_name": "Saquon Barkley",
    "headshot_url": "https://static.www.nfl.com/image/private/f_auto,q_auto/league/o8tlhps5u1tvnaaxlpjk",
    "total_ppr": 223.2,
    "ppr_ppg": 15.9429,
    "consistency_rtg": 0.5031
  },
  {
    "player_id": "00-0035100",
    "player_name": "J.Browning",
    "player_display_name": "Jake Browning",
    "headshot_url": "https://static.www.nfl.com/image/private/f_auto,q_auto/league/tj3i5arbkwbqec9xmnqv",
    "total_ppr": 144.44,
    "ppr_ppg": 16.0489,
    "consistency_rtg": 0.5031
  },
  {
    "player_id": "00-0039075",
    "player_name": "P.Nacua",
    "player_display_name": "Puka Nacua",
    "headshot_url": "https://static.www.nfl.com/image/private/f_auto,q_auto/league/br1ovzclyrebrec6q0mp",
    "total_ppr": 298.5,
    "ppr_ppg": 17.5588,
    "consistency_rtg": 0.5064
  },
  {
    "player_id": "00-0038621",
    "player_name": "D.Douglas",
    "player_display_name": "Demario Douglas",
    "headshot_url": "https://static.www.nfl.com/image/private/f_auto,q_auto/league/svnh61ottqtfmcqvnbj3",
    "total_ppr": 107.2,
    "ppr_ppg": 7.6571,
    "consistency_rtg": 0.5071
  },
  {
    "player_id": "00-0034348",
    "player_name": "C.Sutton",
    "player_display_name": "Courtland Sutton",
    "headshot_url": "https://static.www.nfl.com/image/private/f_auto,q_auto/league/uusaguvnkfv2gt7goale",
    "total_ppr": 190.2,
    "ppr_ppg": 11.8875,
    "consistency_rtg": 0.5112
  },
  {
    "player_id": "00-0033526",
    "player_name": "S.Perine",
    "player_display_name": "Samaje Perine",
    "headshot_url": "https://static.www.nfl.com/image/private/f_auto,q_auto/league/kpdo0ztyzhjobhk4p29a",
    "total_ppr": 121.3,
    "ppr_ppg": 7.1353,
    "consistency_rtg": 0.5125
  },
  {
    "player_id": "00-0036973",
    "player_name": "T.Etienne",
    "player_display_name": "Travis Etienne",
    "headshot_url": "https://static.www.nfl.com/image/private/f_auto,q_auto/league/ne5lyv8n6elqw77yrz9w",
    "total_ppr": 282.4,
    "ppr_ppg": 16.6118,
    "consistency_rtg": 0.5134
  },
  {
    "player_id": "00-0039064",
    "player_name": "Z.Flowers",
    "player_display_name": "Zay Flowers",
    "headshot_url": "https://static.www.nfl.com/image/private/f_auto,q_auto/league/zvstl5cycvmbbqczemau",
    "total_ppr": 206.4,
    "ppr_ppg": 12.9,
    "consistency_rtg": 0.5149
  },
  {
    "player_id": "00-0035700",
    "player_name": "J.Jacobs",
    "player_display_name": "Josh Jacobs",
    "headshot_url": "https://static.www.nfl.com/image/private/f_auto,q_auto/league/sagoqkubeaz5yht01ow7",
    "total_ppr": 181.1,
    "ppr_ppg": 13.9308,
    "consistency_rtg": 0.5153
  },
  {
    "player_id": "00-0036322",
    "player_name": "J.Jefferson",
    "player_display_name": "Justin Jefferson",
    "headshot_url": "https://static.www.nfl.com/image/private/f_auto,q_auto/league/zdstmm4sloqnichybgja",
    "total_ppr": 204.2,
    "ppr_ppg": 20.42,
    "consistency_rtg": 0.5161
  },
  {
    "player_id": "00-0031408",
    "player_name": "M.Evans",
    "player_display_name": "Mike Evans",
    "headshot_url": "https://static.www.nfl.com/image/private/f_auto,q_auto/league/w6eq27k2xs8vawwgkzbl",
    "total_ppr": 282.5,
    "ppr_ppg": 16.6176,
    "consistency_rtg": 0.5197
  },
  {
    "player_id": "00-0031588",
    "player_name": "S.Diggs",
    "player_display_name": "Stefon Diggs",
    "headshot_url": "https://static.www.nfl.com/image/private/f_auto,q_auto/league/zf6nbnzcfzu4y7yq2nzk",
    "total_ppr": 273.8,
    "ppr_ppg": 16.1059,
    "consistency_rtg": 0.521
  },
  {
    "player_id": "00-0035216",
    "player_name": "D.Johnson",
    "player_display_name": "Diontae Johnson",
    "headshot_url": "https://static.www.nfl.com/image/private/f_auto,q_auto/league/imoqxbyoluisz2tmoral",
    "total_ppr": 152.7,
    "ppr_ppg": 11.7462,
    "consistency_rtg": 0.5217
  },
  {
    "player_id": "00-0035289",
    "player_name": "G.Minshew",
    "player_display_name": "Gardner Minshew",
    "headshot_url": "https://static.www.nfl.com/image/private/f_auto,q_auto/league/gvv8ki5crxio2rxfwzng",
    "total_ppr": 196.2,
    "ppr_ppg": 12.2625,
    "consistency_rtg": 0.523
  },
  {
    "player_id": "00-0038041",
    "player_name": "J.Ferguson",
    "player_display_name": "Jake Ferguson",
    "headshot_url": "https://static.www.nfl.com/image/private/f_auto,q_auto/league/xy9bvf3d9yjprwigiqty",
    "total_ppr": 177.1,
    "ppr_ppg": 10.4176,
    "consistency_rtg": 0.5245
  },
  {
    "player_id": "00-0034270",
    "player_name": "T.Conklin",
    "player_display_name": "Tyler Conklin",
    "headshot_url": "https://static.www.nfl.com/image/private/f_auto,q_auto/league/fwuvfpsd7hbtqwlcxtn7",
    "total_ppr": 123.1,
    "ppr_ppg": 7.2412,
    "consistency_rtg": 0.5287
  },
  {
    "player_id": "00-0038102",
    "player_name": "K.Pickett",
    "player_display_name": "Kenny Pickett",
    "headshot_url": "https://static.www.nfl.com/image/private/f_auto,q_auto/league/peknn7x68tldbzufhjs6",
    "total_ppr": 110.2,
    "ppr_ppg": 9.1833,
    "consistency_rtg": 0.5314
  },
  {
    "player_id": "00-0039150",
    "player_name": "B.Young",
    "player_display_name": "Bryce Young",
    "headshot_url": "https://static.www.nfl.com/image/private/f_auto,q_auto/league/knekunqi7nlnwgxnelb8",
    "total_ppr": 156.38,
    "ppr_ppg": 9.7737,
    "consistency_rtg": 0.5326
  },
  {
    "player_id": "00-0036970",
    "player_name": "K.Pitts",
    "player_display_name": "Kyle Pitts",
    "headshot_url": "https://static.www.nfl.com/image/private/f_auto,q_auto/league/bimlwqd3sdzuhddiqgff",
    "total_ppr": 137.3,
    "ppr_ppg": 8.0765,
    "consistency_rtg": 0.533
  },
  {
    "player_id": "00-0037746",
    "player_name": "B.Robinson",
    "player_display_name": "Brian Robinson",
    "headshot_url": "https://static.www.nfl.com/image/private/f_auto,q_auto/league/gxcfbuvmooytbn45kvxf",
    "total_ppr": 198.1,
    "ppr_ppg": 13.2067,
    "consistency_rtg": 0.5358
  },
  {
    "player_id": "00-0033881",
    "player_name": "E.Engram",
    "player_display_name": "Evan Engram",
    "headshot_url": "https://static.www.nfl.com/image/private/f_auto,q_auto/league/adr65rbw956sxntlph8a",
    "total_ppr": 230.3,
    "ppr_ppg": 13.5471,
    "consistency_rtg": 0.5367
  },
  {
    "player_id": "00-0039139",
    "player_name": "J.Gibbs",
    "player_display_name": "Jahmyr Gibbs",
    "headshot_url": "https://static.www.nfl.com/image/private/f_auto,q_auto/league/zv22khikt05uc5fzzby9",
    "total_ppr": 242.1,
    "ppr_ppg": 16.14,
    "consistency_rtg": 0.537
  },
  {
    "player_id": "00-0034960",
    "player_name": "J.Meyers",
    "player_display_name": "Jakobi Meyers",
    "headshot_url": "https://static.www.nfl.com/image/private/f_auto,q_auto/league/lhfd2xsufgep72sfkacg",
    "total_ppr": 218.58,
    "ppr_ppg": 13.6613,
    "consistency_rtg": 0.5384
  },
  {
    "player_id": "00-0030279",
    "player_name": "K.Allen",
    "player_display_name": "Keenan Allen",
    "headshot_url": "https://static.www.nfl.com/image/private/f_auto,q_auto/league/xs7h2igf85nta81v7zb8",
    "total_ppr": 278.86,
    "ppr_ppg": 21.4508,
    "consistency_rtg": 0.5411
  },
  {
    "player_id": "00-0038542",
    "player_name": "B.Robinson",
    "player_display_name": "Bijan Robinson",
    "headshot_url": "https://static.www.nfl.com/image/private/f_auto,q_auto/league/gatvdlb0kch6kyhhpu4c",
    "total_ppr": 246.3,
    "ppr_ppg": 14.4882,
    "consistency_rtg": 0.5416
  },
  {
    "player_id": "00-0036275",
    "player_name": "D.Swift",
    "player_display_name": "D'Andre Swift",
    "headshot_url": "https://static.www.nfl.com/image/private/f_auto,q_auto/league/qehlr75ike82kyxy8j9a",
    "total_ppr": 199.3,
    "ppr_ppg": 12.4563,
    "consistency_rtg": 0.5424
  },
  {
    "player_id": "00-0036980",
    "player_name": "E.Moore",
    "player_display_name": "Elijah Moore",
    "headshot_url": "https://static.www.nfl.com/image/private/f_auto,q_auto/league/bhwvzckfhhcqhb7zdqyj",
    "total_ppr": 132.1,
    "ppr_ppg": 8.2562,
    "consistency_rtg": 0.5433
  },
  {
    "player_id": "00-0033553",
    "player_name": "J.Conner",
    "player_display_name": "James Conner",
    "headshot_url": "https://static.www.nfl.com/image/private/f_auto,q_auto/league/rmqdvrhlmhhyyrhp3vyu",
    "total_ppr": 201.5,
    "ppr_ppg": 15.5,
    "consistency_rtg": 0.5444
  },
  {
    "player_id": "00-0033949",
    "player_name": "J.Dobbs",
    "player_display_name": "Joshua Dobbs",
    "headshot_url": "https://static.www.nfl.com/image/upload/f_auto,q_auto/league/il6zhynxgyun9uvsofgr",
    "total_ppr": 202.66,
    "ppr_ppg": 15.5892,
    "consistency_rtg": 0.5459
  },
  {
    "player_id": "00-0030506",
    "player_name": "T.Kelce",
    "player_display_name": "Travis Kelce",
    "headshot_url": "https://static.www.nfl.com/image/private/f_auto,q_auto/league/ryzr3vbragwe50vtj9af",
    "total_ppr": 219.4,
    "ppr_ppg": 14.6267,
    "consistency_rtg": 0.5472
  },
  {
    "player_id": "00-0039065",
    "player_name": "S.LaPorta",
    "player_display_name": "Sam LaPorta",
    "headshot_url": "https://static.www.nfl.com/image/private/f_auto,q_auto/league/svqsmqhfemrnxcheh0ev",
    "total_ppr": 239.3,
    "ppr_ppg": 14.0765,
    "consistency_rtg": 0.5473
  },
  {
    "player_id": "00-0032764",
    "player_name": "D.Henry",
    "player_display_name": "Derrick Henry",
    "headshot_url": "https://static.www.nfl.com/image/private/f_auto,q_auto/league/xpewyoieoj7zeub4fvff",
    "total_ppr": 246.66,
    "ppr_ppg": 14.5094,
    "consistency_rtg": 0.5481
  },
  {
    "player_id": "00-0035640",
    "player_name": "D.Metcalf",
    "player_display_name": "DK Metcalf",
    "headshot_url": "https://static.www.nfl.com/image/private/f_auto,q_auto/league/u4cefcz7gjvby8c2kdkm",
    "total_ppr": 225.4,
    "ppr_ppg": 14.0875,
    "consistency_rtg": 0.5499
  },
  {
    "player_id": "00-0033895",
    "player_name": "G.Everett",
    "player_display_name": "Gerald Everett",
    "headshot_url": "https://static.www.nfl.com/image/private/f_auto,q_auto/league/te11unippqhdc6auox6i",
    "total_ppr": 111.1,
    "ppr_ppg": 7.4067,
    "consistency_rtg": 0.5516
  },
  {
    "player_id": "00-0033885",
    "player_name": "D.Njoku",
    "player_display_name": "David Njoku",
    "headshot_url": "https://static.www.nfl.com/image/private/f_auto,q_auto/league/ilvxwdllivrvwbuj69cm",
    "total_ppr": 201.2,
    "ppr_ppg": 12.575,
    "consistency_rtg": 0.5622
  },
  {
    "player_id": "00-0038134",
    "player_name": "K.Walker",
    "player_display_name": "Kenneth Walker",
    "headshot_url": "https://static.www.nfl.com/image/private/f_auto,q_auto/league/rwdj1bljth8fyojof5dp",
    "total_ppr": 199.4,
    "ppr_ppg": 13.2933,
    "consistency_rtg": 0.5633
  },
  {
    "player_id": "00-0037013",
    "player_name": "Z.Wilson",
    "player_display_name": "Zach Wilson",
    "headshot_url": "https://static.www.nfl.com/image/private/f_auto,q_auto/league/xkio4hljxo2u59rk2bud",
    "total_ppr": 119.94,
    "ppr_ppg": 9.995,
    "consistency_rtg": 0.5645
  },
  {
    "player_id": "00-0033009",
    "player_name": "T.Boyd",
    "player_display_name": "Tyler Boyd",
    "headshot_url": "https://static.www.nfl.com/image/private/f_auto,q_auto/league/vconwllovf9jqxpu9mow",
    "total_ppr": 144.8,
    "ppr_ppg": 8.5176,
    "consistency_rtg": 0.5681
  },
  {
    "player_id": "00-0036442",
    "player_name": "J.Burrow",
    "player_display_name": "Joe Burrow",
    "headshot_url": "https://static.www.nfl.com/image/private/f_auto,q_auto/league/jzzqz5ubkilrn9dpxtlp",
    "total_ppr": 147.16,
    "ppr_ppg": 14.716,
    "consistency_rtg": 0.5728
  },
  {
    "player_id": "00-0036875",
    "player_name": "R.Stevenson",
    "player_display_name": "Rhamondre Stevenson",
    "headshot_url": "https://static.www.nfl.com/image/private/f_auto,q_auto/league/ro2fqabc4qndtnxykvm7",
    "total_ppr": 145.7,
    "ppr_ppg": 12.1417,
    "consistency_rtg": 0.5732
  },
  {
    "player_id": "00-0038997",
    "player_name": "J.Downs",
    "player_display_name": "Josh Downs",
    "headshot_url": "https://static.www.nfl.com/image/private/f_auto,q_auto/league/wdrwbumtvwv8s9te8wof",
    "total_ppr": 157.1,
    "ppr_ppg": 9.2412,
    "consistency_rtg": 0.5756
  },
  {
    "player_id": "00-0036290",
    "player_name": "C.Kmet",
    "player_display_name": "Cole Kmet",
    "headshot_url": "https://static.www.nfl.com/image/private/f_auto,q_auto/league/ruq1ttpmssyydj0hxwfn",
    "total_ppr": 181.1,
    "ppr_ppg": 12.0733,
    "consistency_rtg": 0.576
  },
  {
    "player_id": "00-0036988",
    "player_name": "J.Palmer",
    "player_display_name": "Josh Palmer",
    "headshot_url": "https://static.www.nfl.com/image/private/f_auto,q_auto/league/bbvzvwnb52cghz4fqyut",
    "total_ppr": 106.7,
    "ppr_ppg": 10.67,
    "consistency_rtg": 0.5781
  },
  {
    "player_id": "00-0037077",
    "player_name": "S.Howell",
    "player_display_name": "Sam Howell",
    "headshot_url": "https://static.www.nfl.com/image/private/f_auto,q_auto/league/inzmmlbrqwjjpjr2zsmd",
    "total_ppr": 257.54,
    "ppr_ppg": 15.1494,
    "consistency_rtg": 0.583
  },
  {
    "player_id": "00-0033699",
    "player_name": "A.Ekeler",
    "player_display_name": "Austin Ekeler",
    "headshot_url": "https://static.www.nfl.com/image/private/f_auto,q_auto/league/s1e7ejmmjkaxbv9zhvfl",
    "total_ppr": 185.4,
    "ppr_ppg": 13.2429,
    "consistency_rtg": 0.5837
  },
  {
    "player_id": "00-0033293",
    "player_name": "A.Jones",
    "player_display_name": "Aaron Jones",
    "headshot_url": "https://static.www.nfl.com/image/private/f_auto,q_auto/league/oo8yixhsahh4gznox7th",
    "total_ppr": 134.9,
    "ppr_ppg": 12.2636,
    "consistency_rtg": 0.5879
  },
  {
    "player_id": "00-0035662",
    "player_name": "M.Brown",
    "player_display_name": "Marquise Brown",
    "headshot_url": "https://static.www.nfl.com/image/private/f_auto,q_auto/league/wgxeuyqliuweurzeigyh",
    "total_ppr": 134.7,
    "ppr_ppg": 10.3615,
    "consistency_rtg": 0.5883
  },
  {
    "player_id": "00-0037809",
    "player_name": "C.Okonkwo",
    "player_display_name": "Chigoziem Okonkwo",
    "headshot_url": "https://static.www.nfl.com/image/private/f_auto,q_auto/league/hkqd6pubp52djhxhtyqi",
    "total_ppr": 113.4,
    "ppr_ppg": 6.6706,
    "consistency_rtg": 0.5911
  },
  {
    "player_id": "00-0037816",
    "player_name": "R.Doubs",
    "player_display_name": "Romeo Doubs",
    "headshot_url": "https://static.www.nfl.com/image/private/f_auto,q_auto/league/pk4dvgjaicaupntsdnnp",
    "total_ppr": 174.4,
    "ppr_ppg": 10.2588,
    "consistency_rtg": 0.5914
  },
  {
    "player_id": "00-0038977",
    "player_name": "T.Dell",
    "player_display_name": "Tank Dell",
    "headshot_url": "https://static.www.nfl.com/image/private/f_auto,q_auto/league/vxkqythvtp5ujzpqlvsk",
    "total_ppr": 165,
    "ppr_ppg": 16.5,
    "consistency_rtg": 0.5933
  },
  {
    "player_id": "00-0036893",
    "player_name": "N.Harris",
    "player_display_name": "Najee Harris",
    "headshot_url": "https://static.www.nfl.com/image/private/f_auto,q_auto/league/hj3n6gjshilgmesahdxs",
    "total_ppr": 195.5,
    "ppr_ppg": 11.5,
    "consistency_rtg": 0.595
  },
  {
    "player_id": "00-0035676",
    "player_name": "A.Brown",
    "player_display_name": "A.J. Brown",
    "headshot_url": "https://static.www.nfl.com/image/private/f_auto,q_auto/league/a014sgzctarbvhwb35lw",
    "total_ppr": 289.6,
    "ppr_ppg": 17.0353,
    "consistency_rtg": 0.6007
  },
  {
    "player_id": "00-0034972",
    "player_name": "A.Mattison",
    "player_display_name": "Alexander Mattison",
    "headshot_url": "https://static.www.nfl.com/image/private/f_auto,q_auto/league/kn3cwf59lqoyauoqmghm",
    "total_ppr": 133.2,
    "ppr_ppg": 8.325,
    "consistency_rtg": 0.6031
  },
  {
    "player_id": "00-0031687",
    "player_name": "R.Mostert",
    "player_display_name": "Raheem Mostert",
    "headshot_url": "https://static.www.nfl.com/image/private/f_auto,q_auto/league/jt7n28bmkyobsxmdbvqu",
    "total_ppr": 267.7,
    "ppr_ppg": 17.8467,
    "consistency_rtg": 0.6032
  },
  {
    "player_id": "00-0032211",
    "player_name": "T.Lockett",
    "player_display_name": "Tyler Lockett",
    "headshot_url": "https://static.www.nfl.com/image/private/f_auto,q_auto/league/f9wttnkcqc2scahf9oth",
    "total_ppr": 202.4,
    "ppr_ppg": 11.9059,
    "consistency_rtg": 0.6041
  },
  {
    "player_id": "00-0039032",
    "player_name": "T.Spears",
    "player_display_name": "Tyjae Spears",
    "headshot_url": "https://static.www.nfl.com/image/private/f_auto,q_auto/league/eeh5mowhlf3godvrceym",
    "total_ppr": 153.8,
    "ppr_ppg": 9.0471,
    "consistency_rtg": 0.6051
  },
  {
    "player_id": "00-0033923",
    "player_name": "K.Hunt",
    "player_display_name": "Kareem Hunt",
    "headshot_url": "https://static.www.nfl.com/image/private/f_auto,q_auto/league/fmy9cgin9nv7ewyhsipr",
    "total_ppr": 118.5,
    "ppr_ppg": 7.9,
    "consistency_rtg": 0.6059
  },
  {
    "player_id": "00-0033045",
    "player_name": "E.Elliott",
    "player_display_name": "Ezekiel Elliott",
    "headshot_url": "https://static.www.nfl.com/image/upload/f_auto,q_auto/league/qf0zgze0wkbvu9rlvolf",
    "total_ppr": 174.5,
    "ppr_ppg": 10.2647,
    "consistency_rtg": 0.6069
  },
  {
    "player_id": "00-0037248",
    "player_name": "J.Cook",
    "player_display_name": "James Cook",
    "headshot_url": "https://static.www.nfl.com/image/private/f_auto,q_auto/league/clqdllqqmpleidegprep",
    "total_ppr": 232.7,
    "ppr_ppg": 13.6882,
    "consistency_rtg": 0.6076
  },
  {
    "player_id": "00-0038933",
    "player_name": "D.Kincaid",
    "player_display_name": "Dalton Kincaid",
    "headshot_url": "https://static.www.nfl.com/image/private/f_auto,q_auto/league/gc2do3ceqflw2axa6xii",
    "total_ppr": 150.3,
    "ppr_ppg": 9.3938,
    "consistency_rtg": 0.6085
  },
  {
    "player_id": "00-0031610",
    "player_name": "D.Waller",
    "player_display_name": "Darren Waller",
    "headshot_url": "https://static.www.nfl.com/image/private/f_auto,q_auto/league/qqzht46a66zbi9xyylf4",
    "total_ppr": 113.2,
    "ppr_ppg": 9.4333,
    "consistency_rtg": 0.6221
  },
  {
    "player_id": "00-0038117",
    "player_name": "W.Robinson",
    "player_display_name": "Wan'Dale Robinson",
    "headshot_url": "https://static.www.nfl.com/image/private/f_auto,q_auto/league/wjr53ffhc3gunx0fs3kp",
    "total_ppr": 133.2,
    "ppr_ppg": 8.88,
    "consistency_rtg": 0.6286
  },
  {
    "player_id": "00-0038579",
    "player_name": "A.O'Connell",
    "player_display_name": "Aidan O'Connell",
    "headshot_url": "https://static.www.nfl.com/image/private/f_auto,q_auto/league/n21t86lqmpiki9vbix3q",
    "total_ppr": 125.82,
    "ppr_ppg": 11.4382,
    "consistency_rtg": 0.6373
  },
  {
    "player_id": "00-0036554",
    "player_name": "N.Collins",
    "player_display_name": "Nico Collins",
    "headshot_url": "https://static.www.nfl.com/image/private/f_auto,q_auto/league/iyfqbpftpdxtwst9wtda",
    "total_ppr": 260.4,
    "ppr_ppg": 17.36,
    "consistency_rtg": 0.6387
  },
  {
    "player_id": "00-0030564",
    "player_name": "D.Hopkins",
    "player_display_name": "DeAndre Hopkins",
    "headshot_url": "https://static.www.nfl.com/image/upload/f_auto,q_auto/league/jgatj8mtftu06pegapip",
    "total_ppr": 223.6,
    "ppr_ppg": 13.1529,
    "consistency_rtg": 0.6531
  },
  {
    "player_id": "00-0033908",
    "player_name": "C.Kupp",
    "player_display_name": "Cooper Kupp",
    "headshot_url": "https://static.www.nfl.com/image/private/f_auto,q_auto/league/bkahtsjkvnom1sbnb6xm",
    "total_ppr": 164.4,
    "ppr_ppg": 13.7,
    "consistency_rtg": 0.6545
  },
  {
    "player_id": "00-0033282",
    "player_name": "C.Samuel",
    "player_display_name": "Curtis Samuel",
    "headshot_url": "https://static.www.nfl.com/image/private/f_auto,q_auto/league/r71vsqs2fg7bvbt1jvzd",
    "total_ppr": 157.2,
    "ppr_ppg": 9.825,
    "consistency_rtg": 0.6568
  },
  {
    "player_id": "00-0038120",
    "player_name": "B.Hall",
    "player_display_name": "Breece Hall",
    "headshot_url": "https://static.www.nfl.com/image/private/f_auto,q_auto/league/a6gggxrcgcacgggh0vme",
    "total_ppr": 290.5,
    "ppr_ppg": 17.0882,
    "consistency_rtg": 0.6608
  },
  {
    "player_id": "00-0034837",
    "player_name": "C.Ridley",
    "player_display_name": "Calvin Ridley",
    "headshot_url": "https://static.www.nfl.com/image/private/f_auto,q_auto/league/jnknuowszoqaywqoopy7",
    "total_ppr": 229.9,
    "ppr_ppg": 13.5235,
    "consistency_rtg": 0.662
  },
  {
    "player_id": "00-0035719",
    "player_name": "D.Samuel",
    "player_display_name": "Deebo Samuel",
    "headshot_url": "https://static.www.nfl.com/image/private/f_auto,q_auto/league/ciwaktyqewczcquks4wy",
    "total_ppr": 243.7,
    "ppr_ppg": 16.2467,
    "consistency_rtg": 0.6629
  },
  {
    "player_id": "00-0038122",
    "player_name": "D.Ridder",
    "player_display_name": "Desmond Ridder",
    "headshot_url": "https://static.www.nfl.com/image/private/f_auto,q_auto/league/ecsb4rwmhlotdjjhyaoq",
    "total_ppr": 181.14,
    "ppr_ppg": 12.076,
    "consistency_rtg": 0.6639
  },
  {
    "player_id": "00-0038994",
    "player_name": "J.Addison",
    "player_display_name": "Jordan Addison",
    "headshot_url": "https://static.www.nfl.com/image/private/f_auto,q_auto/league/zhyhkz6wzwhioemhqgbk",
    "total_ppr": 221.3,
    "ppr_ppg": 13.0176,
    "consistency_rtg": 0.6674
  },
  {
    "player_id": "00-0037545",
    "player_name": "R.Shaheed",
    "player_display_name": "Rashid Shaheed",
    "headshot_url": "https://static.www.nfl.com/image/private/f_auto,q_auto/league/y96n1bum9eowfxmt1nbg",
    "total_ppr": 157.6,
    "ppr_ppg": 10.5067,
    "consistency_rtg": 0.6688
  },
  {
    "player_id": "00-0030035",
    "player_name": "A.Thielen",
    "player_display_name": "Adam Thielen",
    "headshot_url": "https://static.www.nfl.com/image/private/f_auto,q_auto/league/kmldtl8p9h7h5dzvkwsw",
    "total_ppr": 231,
    "ppr_ppg": 13.5882,
    "consistency_rtg": 0.6691
  },
  {
    "player_id": "00-0033288",
    "player_name": "G.Kittle",
    "player_display_name": "George Kittle",
    "headshot_url": "https://static.www.nfl.com/image/private/f_auto,q_auto/league/bwx6bvkrxog0yf4h6fw1",
    "total_ppr": 203.2,
    "ppr_ppg": 12.7,
    "consistency_rtg": 0.6701
  },
  {
    "player_id": "00-0039165",
    "player_name": "Z.Charbonnet",
    "player_display_name": "Zach Charbonnet",
    "headshot_url": "https://static.www.nfl.com/image/private/f_auto,q_auto/league/yuddw2o5skwkgvut6wrv",
    "total_ppr": 106.1,
    "ppr_ppg": 6.6313,
    "consistency_rtg": 0.6793
  },
  {
    "player_id": "00-0036936",
    "player_name": "R.Moore",
    "player_display_name": "Rondale Moore",
    "headshot_url": "https://static.www.nfl.com/image/private/f_auto,q_auto/league/yuwcs40qiqunbfrp9nip",
    "total_ppr": 105,
    "ppr_ppg": 6.1765,
    "consistency_rtg": 0.6822
  },
  {
    "player_id": "00-0035250",
    "player_name": "D.Singletary",
    "player_display_name": "Devin Singletary",
    "headshot_url": "https://static.www.nfl.com/image/upload/f_auto,q_auto/league/ulczhsxmhnyrsyjfrhd5",
    "total_ppr": 167.34,
    "ppr_ppg": 9.8435,
    "consistency_rtg": 0.6839
  },
  {
    "player_id": "00-0039152",
    "player_name": "W.Levis",
    "player_display_name": "Will Levis",
    "headshot_url": "https://static.www.nfl.com/image/private/f_auto,q_auto/league/djuun92gl9ryj9qsccuh",
    "total_ppr": 102.02,
    "ppr_ppg": 11.3356,
    "consistency_rtg": 0.6886
  },
  {
    "player_id": "00-0033858",
    "player_name": "J.Smith",
    "player_display_name": "Jonnu Smith",
    "headshot_url": "https://static.www.nfl.com/image/private/f_auto,q_auto/league/hbnnjc8knqoc95vzyol4",
    "total_ppr": 124.2,
    "ppr_ppg": 8.28,
    "consistency_rtg": 0.689
  },
  {
    "player_id": "00-0037238",
    "player_name": "D.London",
    "player_display_name": "Drake London",
    "headshot_url": "https://static.www.nfl.com/image/private/f_auto,q_auto/league/rrwzcsvsfqq9xptp8o48",
    "total_ppr": 174.38,
    "ppr_ppg": 10.8987,
    "consistency_rtg": 0.6929
  },
  {
    "player_id": "00-0034827",
    "player_name": "D.Moore",
    "player_display_name": "D.J. Moore",
    "headshot_url": "https://static.www.nfl.com/image/private/f_auto,q_auto/league/fuhd1intilojmnbx7wjq",
    "total_ppr": 286.5,
    "ppr_ppg": 16.8529,
    "consistency_rtg": 0.6941
  },
  {
    "player_id": "00-0035535",
    "player_name": "D.Slayton",
    "player_display_name": "Darius Slayton",
    "headshot_url": "https://static.www.nfl.com/image/private/f_auto,q_auto/league/emmy86blz71njkcr496b",
    "total_ppr": 151,
    "ppr_ppg": 8.8824,
    "consistency_rtg": 0.6956
  },
  {
    "player_id": "00-0034184",
    "player_name": "G.Edwards",
    "player_display_name": "Gus Edwards",
    "headshot_url": "https://static.www.nfl.com/image/private/f_auto,q_auto/league/tvxpivjku1lbpf7tfafl",
    "total_ppr": 187,
    "ppr_ppg": 11,
    "consistency_rtg": 0.6999
  },
  {
    "player_id": "00-0034351",
    "player_name": "D.Goedert",
    "player_display_name": "Dallas Goedert",
    "headshot_url": "https://static.www.nfl.com/image/private/f_auto,q_auto/league/flzasty1ea7iswbtd0e5",
    "total_ppr": 136.3,
    "ppr_ppg": 9.7357,
    "consistency_rtg": 0.7016
  },
  {
    "player_id": "00-0038124",
    "player_name": "C.Watson",
    "player_display_name": "Christian Watson",
    "headshot_url": "https://static.www.nfl.com/image/private/f_auto,q_auto/league/tpoxhwuhwmbxfossd66s",
    "total_ppr": 101.3,
    "ppr_ppg": 11.2556,
    "consistency_rtg": 0.7019
  },
  {
    "player_id": "00-0036849",
    "player_name": "T.Atwell",
    "player_display_name": "Tutu Atwell",
    "headshot_url": "https://static.www.nfl.com/image/private/f_auto,q_auto/league/h0kk3mtoa4xwdw21lty9",
    "total_ppr": 112.4,
    "ppr_ppg": 8.0286,
    "consistency_rtg": 0.7032
  },
  {
    "player_id": "00-0031260",
    "player_name": "L.Thomas",
    "player_display_name": "Logan Thomas",
    "headshot_url": "https://static.www.nfl.com/image/private/f_auto,q_auto/league/acm0ymhqdzqxdibwjphv",
    "total_ppr": 126.8,
    "ppr_ppg": 7.925,
    "consistency_rtg": 0.7084
  },
  {
    "player_id": "00-0031381",
    "player_name": "D.Adams",
    "player_display_name": "Davante Adams",
    "headshot_url": "https://static.www.nfl.com/image/private/f_auto,q_auto/league/grvqvmdzu2lsbgvqoxku",
    "total_ppr": 265.4,
    "ppr_ppg": 15.6118,
    "consistency_rtg": 0.7116
  },
  {
    "player_id": "00-0033110",
    "player_name": "T.Higbee",
    "player_display_name": "Tyler Higbee",
    "headshot_url": "https://static.www.nfl.com/image/private/f_auto,q_auto/league/vk9c6lr4d1pdt9sr86ua",
    "total_ppr": 108.5,
    "ppr_ppg": 7.2333,
    "consistency_rtg": 0.712
  },
  {
    "player_id": "00-0037744",
    "player_name": "T.McBride",
    "player_display_name": "Trey McBride",
    "headshot_url": "https://static.www.nfl.com/image/private/f_auto,q_auto/league/x7x9ze5msigs8u57ydvl",
    "total_ppr": 181.5,
    "ppr_ppg": 10.6765,
    "consistency_rtg": 0.7132
  },
  {
    "player_id": "00-0036345",
    "player_name": "K.Osborn",
    "player_display_name": "K.J. Osborn",
    "headshot_url": "https://static.www.nfl.com/image/private/f_auto,q_auto/league/rbgsvh08nmm29gaiw7pr",
    "total_ppr": 120,
    "ppr_ppg": 8,
    "consistency_rtg": 0.7151
  },
  {
    "player_id": "00-0038129",
    "player_name": "C.Otton",
    "player_display_name": "Cade Otton",
    "headshot_url": "https://static.www.nfl.com/image/private/f_auto,q_auto/league/vchmryh0myuq67t9ei1u",
    "total_ppr": 116.5,
    "ppr_ppg": 7.2812,
    "consistency_rtg": 0.7178
  },
  {
    "player_id": "00-0034383",
    "player_name": "D.Schultz",
    "player_display_name": "Dalton Schultz",
    "headshot_url": "https://static.www.nfl.com/image/private/f_auto,q_auto/league/lhplapyya8pp3yyz8bht",
    "total_ppr": 150.5,
    "ppr_ppg": 10.0333,
    "consistency_rtg": 0.7284
  },
  {
    "player_id": "00-0031235",
    "player_name": "O.Beckham",
    "player_display_name": "Odell Beckham",
    "headshot_url": "https://static.www.nfl.com/image/private/f_auto,q_auto/league/etl34lkiscs2lpc4to2f",
    "total_ppr": 107.5,
    "ppr_ppg": 7.6786,
    "consistency_rtg": 0.7417
  },
  {
    "player_id": "00-0036251",
    "player_name": "Z.Moss",
    "player_display_name": "Zack Moss",
    "headshot_url": "https://static.www.nfl.com/image/private/f_auto,q_auto/league/ds6hvcx6s1vqihnaumm9",
    "total_ppr": 169.6,
    "ppr_ppg": 12.1143,
    "consistency_rtg": 0.7463
  },
  {
    "player_id": "00-0039021",
    "player_name": "R.Johnson",
    "player_display_name": "Roschon Johnson",
    "headshot_url": "https://static.www.nfl.com/image/private/f_auto,q_auto/league/oahmdtjp5ufvbk8dimws",
    "total_ppr": 102.1,
    "ppr_ppg": 6.8067,
    "consistency_rtg": 0.7481
  },
  {
    "player_id": "00-0037247",
    "player_name": "G.Pickens",
    "player_display_name": "George Pickens",
    "headshot_url": "https://static.www.nfl.com/image/private/f_auto,q_auto/league/gnfxhtk8e6ecazbhoinl",
    "total_ppr": 208.8,
    "ppr_ppg": 12.2824,
    "consistency_rtg": 0.7486
  },
  {
    "player_id": "00-0037263",
    "player_name": "T.Allgeier",
    "player_display_name": "Tyler Allgeier",
    "headshot_url": "https://static.www.nfl.com/image/private/f_auto,q_auto/league/u5aztfcvemiyxt9lisic",
    "total_ppr": 137.6,
    "ppr_ppg": 8.0941,
    "consistency_rtg": 0.7515
  },
  {
    "player_id": "00-0031236",
    "player_name": "B.Cooks",
    "player_display_name": "Brandin Cooks",
    "headshot_url": "https://static.www.nfl.com/image/private/f_auto,q_auto/league/wy6qidqm8jjp6buvu3lp",
    "total_ppr": 173.2,
    "ppr_ppg": 10.825,
    "consistency_rtg": 0.7537
  },
  {
    "player_id": "00-0036900",
    "player_name": "J.Chase",
    "player_display_name": "Ja'Marr Chase",
    "headshot_url": "https://static.www.nfl.com/image/private/f_auto,q_auto/league/xqhrnv1bfpl2zmhpqobq",
    "total_ppr": 262.72,
    "ppr_ppg": 16.42,
    "consistency_rtg": 0.762
  },
  {
    "player_id": "00-0033090",
    "player_name": "H.Henry",
    "player_display_name": "Hunter Henry",
    "headshot_url": "https://static.www.nfl.com/image/private/f_auto,q_auto/league/sdjob9akppefyo7py5tj",
    "total_ppr": 119.9,
    "ppr_ppg": 9.2231,
    "consistency_rtg": 0.7649
  },
  {
    "player_id": "00-0036906",
    "player_name": "K.Herbert",
    "player_display_name": "Khalil Herbert",
    "headshot_url": "https://static.www.nfl.com/image/private/f_auto,q_auto/league/ovmznomieqta3a4rgx9a",
    "total_ppr": 112.5,
    "ppr_ppg": 9.375,
    "consistency_rtg": 0.7875
  },
  {
    "player_id": "00-0033943",
    "player_name": "J.Reynolds",
    "player_display_name": "Josh Reynolds",
    "headshot_url": "https://static.www.nfl.com/image/private/f_auto,q_auto/league/sxrgouqg155xtgtzesy9",
    "total_ppr": 128.8,
    "ppr_ppg": 8.05,
    "consistency_rtg": 0.7887
  },
  {
    "player_id": "00-0038393",
    "player_name": "D.Wicks",
    "player_display_name": "Dontayvion Wicks",
    "headshot_url": "https://static.www.nfl.com/image/private/f_auto,q_auto/league/cnldfuaj4ifhgjpuzyte",
    "total_ppr": 119.76,
    "ppr_ppg": 7.984,
    "consistency_rtg": 0.8016
  },
  {
    "player_id": "00-0033357",
    "player_name": "T.Hill",
    "player_display_name": "Taysom Hill",
    "headshot_url": "https://static.www.nfl.com/image/private/f_auto,q_auto/league/pjp1aahvacigoh0sorpg",
    "total_ppr": 143.52,
    "ppr_ppg": 8.97,
    "consistency_rtg": 0.803
  },
  {
    "player_id": "00-0034975",
    "player_name": "J.Hill",
    "player_display_name": "Justice Hill",
    "headshot_url": "https://static.www.nfl.com/image/private/f_auto,q_auto/league/v9xufmbbfauthnlpxcrc",
    "total_ppr": 109.3,
    "ppr_ppg": 6.8313,
    "consistency_rtg": 0.8115
  },
  {
    "player_id": "00-0031544",
    "player_name": "A.Cooper",
    "player_display_name": "Amari Cooper",
    "headshot_url": "https://static.www.nfl.com/image/private/f_auto,q_auto/league/zibbxjtein7gpu5zgcj4",
    "total_ppr": 227,
    "ppr_ppg": 15.1333,
    "consistency_rtg": 0.8217
  },
  {
    "player_id": "00-0038559",
    "player_name": "M.Wilson",
    "player_display_name": "Michael Wilson",
    "headshot_url": "https://static.www.nfl.com/image/private/f_auto,q_auto/league/o5sshsrygioektzjsahk",
    "total_ppr": 114.5,
    "ppr_ppg": 8.8077,
    "consistency_rtg": 0.8304
  },
  {
    "player_id": "00-0039040",
    "player_name": "D.Achane",
    "player_display_name": "Devon Achane",
    "headshot_url": "https://static.www.nfl.com/image/private/f_auto,q_auto/league/ywxugcuxwj4msieu6n25",
    "total_ppr": 190.7,
    "ppr_ppg": 17.3364,
    "consistency_rtg": 0.8446
  },
  {
    "player_id": "00-0037276",
    "player_name": "T.Chandler",
    "player_display_name": "Ty Chandler",
    "headshot_url": "https://static.www.nfl.com/image/private/f_auto,q_auto/league/map979dvuonzb8a6g13b",
    "total_ppr": 101,
    "ppr_ppg": 7.7692,
    "consistency_rtg": 0.8501
  },
  {
    "player_id": "00-0036972",
    "player_name": "M.Jones",
    "player_display_name": "Mac Jones",
    "headshot_url": "https://static.www.nfl.com/image/private/f_auto,q_auto/league/fillvwo9xf7paiwbfihk",
    "total_ppr": 106.4,
    "ppr_ppg": 9.6727,
    "consistency_rtg": 0.8549
  },
  {
    "player_id": "00-0036410",
    "player_name": "T.Higgins",
    "player_display_name": "Tee Higgins",
    "headshot_url": "https://static.www.nfl.com/image/private/f_auto,q_auto/league/fkpf9urirrkqkln7d2n9",
    "total_ppr": 137.6,
    "ppr_ppg": 11.4667,
    "consistency_rtg": 0.8553
  },
  {
    "player_id": "00-0037261",
    "player_name": "K.Shakir",
    "player_display_name": "Khalil Shakir",
    "headshot_url": "https://static.www.nfl.com/image/private/f_auto,q_auto/league/l1flqgo30hfowrdckdeu",
    "total_ppr": 113.1,
    "ppr_ppg": 7.0687,
    "consistency_rtg": 0.8668
  },
  {
    "player_id": "00-0034777",
    "player_name": "D.Chark",
    "player_display_name": "D.J. Chark",
    "headshot_url": "https://static.www.nfl.com/image/private/f_auto,q_auto/league/bn5lxiv1cyyidlhkth84",
    "total_ppr": 115.5,
    "ppr_ppg": 8.25,
    "consistency_rtg": 0.8711
  },
  {
    "player_id": "00-0038794",
    "player_name": "J.McLaughlin",
    "player_display_name": "Jaleel McLaughlin",
    "headshot_url": "https://static.www.nfl.com/image/private/f_auto,q_auto/league/ba28phgfwcntbca7aoyh",
    "total_ppr": 106,
    "ppr_ppg": 6.2353,
    "consistency_rtg": 0.8839
  },
  {
    "player_id": "00-0037741",
    "player_name": "J.Dotson",
    "player_display_name": "Jahan Dotson",
    "headshot_url": "https://static.www.nfl.com/image/private/f_auto,q_auto/league/z768onjtm135fjjmeney",
    "total_ppr": 124.8,
    "ppr_ppg": 7.3412,
    "consistency_rtg": 0.8932
  },
  {
    "player_id": "00-0037838",
    "player_name": "I.Likely",
    "player_display_name": "Isaiah Likely",
    "headshot_url": "https://static.www.nfl.com/image/private/f_auto,q_auto/league/z8xwspdtqixrzxxjbapx",
    "total_ppr": 101.1,
    "ppr_ppg": 7.7769,
    "consistency_rtg": 0.9019
  },
  {
    "player_id": "00-0036196",
    "player_name": "G.Davis",
    "player_display_name": "Gabe Davis",
    "headshot_url": "https://static.www.nfl.com/image/private/f_auto,q_auto/league/q5ofnb6w7gokbggfmbxp",
    "total_ppr": 161.4,
    "ppr_ppg": 10.0875,
    "consistency_rtg": 0.9524
  },
  {
    "player_id": "00-0033591",
    "player_name": "N.Brown",
    "player_display_name": "Noah Brown",
    "headshot_url": "https://static.www.nfl.com/image/upload/f_auto,q_auto/league/skdu8rnw7nwgxdkaonyi",
    "total_ppr": 101.6,
    "ppr_ppg": 10.16,
    "consistency_rtg": 1.0235
  }
]
